llama_index/py.typed
llama_index/vector_stores/redis/__init__.py
llama_index/vector_stores/redis/base.py
llama_index/vector_stores/redis/schema.py
llama_index/vector_stores/redis/utils.py
basejump_llama_index_vector_stores_redis-0.5.1.post2.dist-info/METADATA
basejump_llama_index_vector_stores_redis-0.5.1.post2.dist-info/WHEEL
basejump_llama_index_vector_stores_redis-0.5.1.post2.dist-info/licenses/LICENSE
basejump_llama_index_vector_stores_redis-0.5.1.post2.dist-info/RECORD
